d2r_loot_reader-0.1.0.dist-info/licenses/LICENSE
d2rlootreader/__init__.py
d2rlootreader/__main__.py
d2rlootreader/cfg.py
d2rlootreader/cli.py
d2rlootreader/item_parser.py
d2rlootreader/region_selector.py
d2rlootreader/screen.py
d2rlootreader/repository/affixes.json
d2rlootreader/repository/bases.json
d2rlootreader/repository/classes.json
d2rlootreader/repository/magic.json
d2rlootreader/repository/rares.json
d2rlootreader/repository/requirements.json
d2rlootreader/repository/runewords.json
d2rlootreader/repository/set.json
d2rlootreader/repository/skills.json
d2rlootreader/repository/stats.json
d2rlootreader/repository/uniques.json
d2rlootreader/tessdata/d2r.traineddata
d2r_loot_reader-0.1.0.dist-info/METADATA
d2r_loot_reader-0.1.0.dist-info/WHEEL
d2r_loot_reader-0.1.0.dist-info/entry_points.txt
d2r_loot_reader-0.1.0.dist-info/top_level.txt
d2r_loot_reader-0.1.0.dist-info/RECORD
