Metadata-Version: 2.4
Name: d2r-loot-reader
Version: 0.1.0
Summary: Diablo II: Resurrected Loot Tooltip Reader
Author: Lucjan Dudek
License-Expression: GPL-3.0-or-later
Project-URL: Homepage, https://github.com/lucekdudek/d2r-loot-reader
Project-URL: Bug Tracker, https://github.com/lucekdudek/d2r-loot-reader/issues
Classifier: Programming Language :: Python :: 3
Classifier: Operating System :: OS Independent
Requires-Python: >=3.8
License-File: LICENSE
Requires-Dist: mss
Requires-Dist: numpy
Requires-Dist: opencv-python
Requires-Dist: Pillow
Requires-Dist: pytesseract
Requires-Dist: rapidfuzz
Provides-Extra: dev
Requires-Dist: black; extra == "dev"
Requires-Dist: isort; extra == "dev"
Requires-Dist: pytest; extra == "dev"
Dynamic: license-file
